Metadata-Version: 2.1
Name: cvargs
Version: 0.1.0
Summary: Function argument conversion
Home-page: https://gitlab.com/diefans/cvargs
Author: Oliver Berger
Author-email: diefans@gmail.com
License: UNKNOWN
Platform: UNKNOWN
Classifier: Programming Language :: Python :: 3.7
Classifier: Programming Language :: Python :: 3.8
Classifier: License :: OSI Approved :: Apache Software License
Classifier: License :: OSI Approved :: MIT License
Requires-Python: >=3.7,<4.0
Provides-Extra: tests
